setup.py
handyfunc/__init__.py
handyfunc/bayesian_average.py
handyfunc/cosing_sim.py
handyfunc/data2binary.py
handyfunc/get_keys.py
handyfunc/get_pretokens.py
handyfunc/print_runtime.py
utilsfunc.egg-info/PKG-INFO
utilsfunc.egg-info/SOURCES.txt
utilsfunc.egg-info/dependency_links.txt
utilsfunc.egg-info/requires.txt
utilsfunc.egg-info/top_level.txt