Metadata-Version: 1.0
Name: utilsfunc
Version: 0.1.2
Summary: Some handy functions help you to easy working
Home-page: UNKNOWN
Author: UNKNOWN
Author-email: UNKNOWN
License: UNKNOWN
Platform: UNKNOWN
